fhire/__init__.py
fhire/exceptions.py
fhire/classes/__init__.py
fhire/classes/fhire.py
fhire/fhire_base/__init__.py
fhire/fhire_base/observation.py
fhire/fhire_base/patient.py
fhire/fhire_base/procedure.py
fhire/fhire_pojo/__init__.py
fhire/fhire_pojo/observation/__init__.py
fhire/fhire_pojo/observation/get_observation.py
fhire/fhire_pojo/observation/post_observation.py
fhire/fhire_pojo/patient/__init__.py
fhire/fhire_pojo/patient/create_patient_response.py
fhire/fhire_pojo/patient/get_patient_response.py
fhire/fhire_pojo/procedure/__init__.py
fhire/fhire_pojo/procedure/get_procedure.py
fhire/fhire_pojo/procedure/post_procedure.py
fhire/tests/__init__.py
fhire/tests/test_fhire_patient/__init__.py
Fhire-0.0.9.dist-info/METADATA
Fhire-0.0.9.dist-info/WHEEL
Fhire-0.0.9.dist-info/top_level.txt
Fhire-0.0.9.dist-info/RECORD
